detspace/__init__.py
detspace/generator.py
detspace/utils.py
detspace-0.0.1.dist-info/METADATA
detspace-0.0.1.dist-info/WHEEL
detspace-0.0.1.dist-info/top_level.txt
detspace-0.0.1.dist-info/RECORD
