Metadata-Version: 2.1
Name: detspace
Version: 0.0.1
Summary: DetSpace package module
Author: Hèctor Martín
Keywords: python,metabolic expasion
Classifier: Development Status :: 3 - Alpha
Classifier: Intended Audience :: Science/Research
Classifier: Programming Language :: Python :: 3
Classifier: Operating System :: Unix
Classifier: Operating System :: MacOS
Classifier: Operating System :: Microsoft
